<?xml version="1.0" encoding="UTF-8" standalone="no"?>
<!DOCTYPE eAdventure PUBLIC "SYSTEM" "eadventure.dtd">
<eAdventure version="1">
  <player>
    <resources name="No name">
      <asset type="standup" uri="assets/special/EmptyAnimation" />
      <asset type="standdown" uri="assets/special/EmptyAnimation" />
      <asset type="standright" uri="assets/special/EmptyAnimation" />
      <asset type="standleft" uri="assets/special/EmptyAnimation" />
      <asset type="speakup" uri="assets/special/EmptyAnimation" />
      <asset type="speakdown" uri="assets/special/EmptyAnimation" />
      <asset type="speakright" uri="assets/special/EmptyAnimation" />
      <asset type="speakleft" uri="assets/special/EmptyAnimation" />
      <asset type="useright" uri="assets/special/EmptyAnimation" />
      <asset type="useleft" uri="assets/special/EmptyAnimation" />
      <asset type="walkup" uri="assets/special/EmptyAnimation" />
      <asset type="walkdown" uri="assets/special/EmptyAnimation" />
      <asset type="walkright" uri="assets/special/EmptyAnimation" />
      <asset type="walkleft" uri="assets/special/EmptyAnimation" />
    </resources>
    <textcolor showsSpeechBubble="no" bubbleBkgColor="#FFFFFF" bubbleBorderColor="#000000">
      <frontcolor color="#FFFFFF" />
      <bordercolor color="#000000" />
    </textcolor>
    <description>
      <name>
      </name>
      <brief>
      </brief>
      <detailed>
      </detailed>
    </description>
    <voice name="" synthesizeAlways="no" />
  </player>
  <character id="Dani">
    <resources name="">
      <asset type="standup" uri="assets/animation/Dani2.eaa.xml" />
      <asset type="standdown" uri="assets/animation/Dani1.eaa.xml" />
      <asset type="standright" uri="assets/special/EmptyAnimation" />
      <asset type="standleft" uri="assets/special/EmptyAnimation" />
      <asset type="speakup" uri="assets/special/EmptyAnimation" />
      <asset type="speakdown" uri="assets/special/EmptyAnimation" />
      <asset type="speakright" uri="assets/special/EmptyAnimation" />
      <asset type="speakleft" uri="assets/special/EmptyAnimation" />
      <asset type="useright" uri="assets/special/EmptyAnimation" />
      <asset type="useleft" uri="assets/special/EmptyAnimation" />
      <asset type="walkup" uri="assets/special/EmptyAnimation" />
      <asset type="walkdown" uri="assets/special/EmptyAnimation" />
      <asset type="walkright" uri="assets/special/EmptyAnimation" />
      <asset type="walkleft" uri="assets/special/EmptyAnimation" />
    </resources>
    <textcolor showsSpeechBubble="no" bubbleBkgColor="#FFFFFF" bubbleBorderColor="#000000">
      <frontcolor color="#FFFFFF" />
      <bordercolor color="#000000" />
    </textcolor>
    <description>
      <name>
      </name>
      <brief>
      </brief>
      <detailed>
      </detailed>
    </description>
    <voice name="" synthesizeAlways="no" />
    <actions>
      <talk-to needsGoTo="yes" keepDistance="35" not-effects="no">
        <condition>
          <inactive flag="HablarDaniBurguer" />
          <inactive flag="HacerDesaparecerADaniYEnviarloAlPatio" />
        </condition>
        <effect>
          <trigger-conversation idTarget="primera_conversacion_Dani" />
          <condition />
        </effect>
      </talk-to>
      <talk-to needsGoTo="yes" keepDistance="35" not-effects="no">
        <condition>
          <inactive flag="HablarDaniBurguer" />
          <active flag="HacerDesaparecerADaniYEnviarloAlPatio" />
        </condition>
        <effect>
          <trigger-conversation idTarget="segunda_conversacion_PatioIrAlBurguer" />
          <condition />
        </effect>
      </talk-to>
      <talk-to needsGoTo="yes" keepDistance="35" not-effects="no">
        <effect>
          <trigger-conversation idTarget="quinta_coversacion_DaniEntraAClase" />
          <condition />
        </effect>
      </talk-to>
    </actions>
  </character>
  <character id="Mario">
    <resources name="No name">
      <asset type="standup" uri="assets/animation/MarioUp.eaa.xml" />
      <asset type="standdown" uri="assets/animation/MarioDown.eaa.xml" />
      <asset type="standright" uri="assets/special/EmptyAnimation" />
      <asset type="standleft" uri="assets/special/EmptyAnimation" />
      <asset type="speakup" uri="assets/special/EmptyAnimation" />
      <asset type="speakdown" uri="assets/special/EmptyAnimation" />
      <asset type="speakright" uri="assets/special/EmptyAnimation" />
      <asset type="speakleft" uri="assets/special/EmptyAnimation" />
      <asset type="useright" uri="assets/special/EmptyAnimation" />
      <asset type="useleft" uri="assets/special/EmptyAnimation" />
      <asset type="walkup" uri="assets/special/EmptyAnimation" />
      <asset type="walkdown" uri="assets/special/EmptyAnimation" />
      <asset type="walkright" uri="assets/special/EmptyAnimation" />
      <asset type="walkleft" uri="assets/special/EmptyAnimation" />
    </resources>
    <textcolor showsSpeechBubble="no" bubbleBkgColor="#FFFFFF" bubbleBorderColor="#000000">
      <frontcolor color="#FFFFFF" />
      <bordercolor color="#000000" />
    </textcolor>
    <description>
      <name>
      </name>
      <brief>
      </brief>
      <detailed>
      </detailed>
    </description>
    <voice name="" synthesizeAlways="no" />
  </character>
  <character id="Julia">
    <resources name="No name">
      <asset type="standup" uri="assets/animation/JuliaUp.eaa.xml" />
      <asset type="standdown" uri="assets/animation/JuliaDown.eaa.xml" />
      <asset type="standright" uri="assets/special/EmptyAnimation" />
      <asset type="standleft" uri="assets/special/EmptyAnimation" />
      <asset type="speakup" uri="assets/special/EmptyAnimation" />
      <asset type="speakdown" uri="assets/special/EmptyAnimation" />
      <asset type="speakright" uri="assets/special/EmptyAnimation" />
      <asset type="speakleft" uri="assets/special/EmptyAnimation" />
      <asset type="useright" uri="assets/special/EmptyAnimation" />
      <asset type="useleft" uri="assets/special/EmptyAnimation" />
      <asset type="walkup" uri="assets/special/EmptyAnimation" />
      <asset type="walkdown" uri="assets/special/EmptyAnimation" />
      <asset type="walkright" uri="assets/special/EmptyAnimation" />
      <asset type="walkleft" uri="assets/special/EmptyAnimation" />
    </resources>
    <textcolor showsSpeechBubble="no" bubbleBkgColor="#FFFFFF" bubbleBorderColor="#000000">
      <frontcolor color="#FFFFFF" />
      <bordercolor color="#000000" />
    </textcolor>
    <description>
      <name>
      </name>
      <brief>
      </brief>
      <detailed>
      </detailed>
    </description>
    <voice name="" synthesizeAlways="no" />
  </character>
  <character id="CompañeroClase1">
    <resources name="No name">
      <asset type="standup" uri="assets/animation/Compi1Up.eaa.xml" />
      <asset type="standdown" uri="assets/animation/Compi1Down.eaa.xml" />
      <asset type="standright" uri="assets/special/EmptyAnimation" />
      <asset type="standleft" uri="assets/special/EmptyAnimation" />
      <asset type="speakup" uri="assets/special/EmptyAnimation" />
      <asset type="speakdown" uri="assets/special/EmptyAnimation" />
      <asset type="speakright" uri="assets/special/EmptyAnimation" />
      <asset type="speakleft" uri="assets/special/EmptyAnimation" />
      <asset type="useright" uri="assets/special/EmptyAnimation" />
      <asset type="useleft" uri="assets/special/EmptyAnimation" />
      <asset type="walkup" uri="assets/special/EmptyAnimation" />
      <asset type="walkdown" uri="assets/special/EmptyAnimation" />
      <asset type="walkright" uri="assets/special/EmptyAnimation" />
      <asset type="walkleft" uri="assets/special/EmptyAnimation" />
    </resources>
    <textcolor showsSpeechBubble="no" bubbleBkgColor="#FFFFFF" bubbleBorderColor="#000000">
      <frontcolor color="#FFFFFF" />
      <bordercolor color="#000000" />
    </textcolor>
    <description>
      <name>
      </name>
      <brief>
      </brief>
      <detailed>
      </detailed>
    </description>
    <voice name="" synthesizeAlways="no" />
    <actions>
      <talk-to needsGoTo="yes" keepDistance="35" not-effects="no">
        <effect>
          <trigger-conversation idTarget="cuarta_conversacion_CotilleosCompañeros" />
          <condition />
        </effect>
      </talk-to>
    </actions>
  </character>
  <character id="CompañeroClase2">
    <resources name="No name">
      <asset type="standup" uri="assets/animation/Compi2up.eaa.xml" />
      <asset type="standdown" uri="assets/animation/Compi2Down.eaa.xml" />
      <asset type="standright" uri="assets/special/EmptyAnimation" />
      <asset type="standleft" uri="assets/special/EmptyAnimation" />
      <asset type="speakup" uri="assets/special/EmptyAnimation" />
      <asset type="speakdown" uri="assets/special/EmptyAnimation" />
      <asset type="speakright" uri="assets/special/EmptyAnimation" />
      <asset type="speakleft" uri="assets/special/EmptyAnimation" />
      <asset type="useright" uri="assets/special/EmptyAnimation" />
      <asset type="useleft" uri="assets/special/EmptyAnimation" />
      <asset type="walkup" uri="assets/special/EmptyAnimation" />
      <asset type="walkdown" uri="assets/special/EmptyAnimation" />
      <asset type="walkright" uri="assets/special/EmptyAnimation" />
      <asset type="walkleft" uri="assets/special/EmptyAnimation" />
    </resources>
    <textcolor showsSpeechBubble="no" bubbleBkgColor="#FFFFFF" bubbleBorderColor="#000000">
      <frontcolor color="#FFFFFF" />
      <bordercolor color="#000000" />
    </textcolor>
    <description>
      <name>
      </name>
      <brief>
      </brief>
      <detailed>
      </detailed>
    </description>
    <voice name="" synthesizeAlways="no" />
  </character>
  <character id="CompañeroClase3">
    <resources name="No name">
      <asset type="standup" uri="assets/animation/Compi3up.eaa.xml" />
      <asset type="standdown" uri="assets/animation/Compi3Down.eaa.xml" />
      <asset type="standright" uri="assets/special/EmptyAnimation" />
      <asset type="standleft" uri="assets/special/EmptyAnimation" />
      <asset type="speakup" uri="assets/special/EmptyAnimation" />
      <asset type="speakdown" uri="assets/special/EmptyAnimation" />
      <asset type="speakright" uri="assets/special/EmptyAnimation" />
      <asset type="speakleft" uri="assets/special/EmptyAnimation" />
      <asset type="useright" uri="assets/special/EmptyAnimation" />
      <asset type="useleft" uri="assets/special/EmptyAnimation" />
      <asset type="walkup" uri="assets/special/EmptyAnimation" />
      <asset type="walkdown" uri="assets/special/EmptyAnimation" />
      <asset type="walkright" uri="assets/special/EmptyAnimation" />
      <asset type="walkleft" uri="assets/special/EmptyAnimation" />
    </resources>
    <textcolor showsSpeechBubble="no" bubbleBkgColor="#FFFFFF" bubbleBorderColor="#000000">
      <frontcolor color="#FFFFFF" />
      <bordercolor color="#000000" />
    </textcolor>
    <description>
      <name>
      </name>
      <brief>
      </brief>
      <detailed>
      </detailed>
    </description>
    <voice name="" synthesizeAlways="no" />
  </character>
  <character id="Profesor">
    <resources name="No name">
      <asset type="standup" uri="assets/animation/ProfeUp.eaa.xml" />
      <asset type="standdown" uri="assets/animation/ProfeDown.eaa.xml" />
      <asset type="standright" uri="assets/special/EmptyAnimation" />
      <asset type="standleft" uri="assets/special/EmptyAnimation" />
      <asset type="speakup" uri="assets/special/EmptyAnimation" />
      <asset type="speakdown" uri="assets/special/EmptyAnimation" />
      <asset type="speakright" uri="assets/special/EmptyAnimation" />
      <asset type="speakleft" uri="assets/special/EmptyAnimation" />
      <asset type="useright" uri="assets/special/EmptyAnimation" />
      <asset type="useleft" uri="assets/special/EmptyAnimation" />
      <asset type="walkup" uri="assets/special/EmptyAnimation" />
      <asset type="walkdown" uri="assets/special/EmptyAnimation" />
      <asset type="walkright" uri="assets/special/EmptyAnimation" />
      <asset type="walkleft" uri="assets/special/EmptyAnimation" />
    </resources>
    <textcolor showsSpeechBubble="no" bubbleBkgColor="#FFFFFF" bubbleBorderColor="#000000">
      <frontcolor color="#FFFFFF" />
      <bordercolor color="#000000" />
    </textcolor>
    <description>
      <name>
      </name>
      <brief>
      </brief>
      <detailed>
      </detailed>
    </description>
    <voice name="" synthesizeAlways="no" />
  </character>
  <character id="Madre">
    <resources name="No name">
      <asset type="standup" uri="assets/animation/madreUp.eaa.xml" />
      <asset type="standdown" uri="assets/animation/madreDown.eaa.xml" />
      <asset type="standright" uri="assets/special/EmptyAnimation" />
      <asset type="standleft" uri="assets/special/EmptyAnimation" />
      <asset type="speakup" uri="assets/special/EmptyAnimation" />
      <asset type="speakdown" uri="assets/special/EmptyAnimation" />
      <asset type="speakright" uri="assets/special/EmptyAnimation" />
      <asset type="speakleft" uri="assets/special/EmptyAnimation" />
      <asset type="useright" uri="assets/special/EmptyAnimation" />
      <asset type="useleft" uri="assets/special/EmptyAnimation" />
      <asset type="walkup" uri="assets/special/EmptyAnimation" />
      <asset type="walkdown" uri="assets/special/EmptyAnimation" />
      <asset type="walkright" uri="assets/special/EmptyAnimation" />
      <asset type="walkleft" uri="assets/special/EmptyAnimation" />
    </resources>
    <textcolor showsSpeechBubble="no" bubbleBkgColor="#FFFFFF" bubbleBorderColor="#000000">
      <frontcolor color="#FFFFFF" />
      <bordercolor color="#000000" />
    </textcolor>
    <description>
      <name>
      </name>
      <brief>
      </brief>
      <detailed>
      </detailed>
    </description>
    <voice name="" synthesizeAlways="no" />
  </character>
  <scene id="Titulo" start="yes" playerLayer="-1" playerScale="1" class="accesible" type="area">
    <documentation>
    </documentation>
    <resources name="No name">
      <asset type="background" uri="assets/special/EmptyBackground.png" />
    </resources>
    <name>
    </name>
    <default-initial-position x="400" y="450" />
    <exits>
      <exit rectangular="yes" x="339" y="268" width="100" height="100" hasInfluenceArea="no" idTarget="Clase" destinyY="-2147483648" destinyX="-2147483648" destinyScale="1" transitionType="0" transitionTime="0" not-effects="no">
        <exit-look text="" cursor-path="" sound-path="" />
        <post-effect>
          <set-value var="Animo" value="6" />
          <condition />
        </post-effect>
      </exit>
    </exits>
  </scene>
  <scene id="Clase" start="no" playerLayer="-1" playerScale="1" class="accesible" type="area">
    <documentation>
    </documentation>
    <resources name="clase">
      <asset type="background" uri="assets/background/cole-aula.png" />
    </resources>
    <name>
    </name>
    <default-initial-position x="400" y="450" />
    <exits>
      <exit rectangular="yes" x="1811" y="188" width="117" height="422" hasInfluenceArea="no" idTarget="PasilloColegio" destinyY="-2147483648" destinyX="-2147483648" destinyScale="1" transitionType="0" transitionTime="0" not-effects="yes">
        <exit-look text="" cursor-path="" sound-path="" />
        <condition>
          <either>
            <active flag="HablarDaniBurguer" />
            <active flag="HacerDesaparecerADaniYEnviarloAlPatio" />
          </either>
        </condition>
        <not-effect>
          <speak-player>Debería hablar con Dani para ver que plan tienen hoy.</speak-player>
          <condition />
        </not-effect>
      </exit>
    </exits>
    <characters>
      <character-ref idTarget="Dani" x="565" y="869" scale="0.589029" orientation="0" layer="5" hasInfluenceArea="no">
        <condition>
          <inactive flag="HablarDaniBurguer" />
          <inactive flag="HacerDesaparecerADaniYEnviarloAlPatio" />
        </condition>
      </character-ref>
      <character-ref idTarget="CompañeroClase1" x="1034" y="589" scale="0.4054624" orientation="2" layer="1" hasInfluenceArea="no">
        <condition>
          <inactive flag="EntraProfesor" />
          <active flag="Dia2" />
        </condition>
      </character-ref>
      <character-ref idTarget="CompañeroClase2" x="928" y="639" scale="0.4877297" orientation="0" layer="2" hasInfluenceArea="no">
        <condition>
          <inactive flag="EntraProfesor" />
          <active flag="Dia2" />
        </condition>
      </character-ref>
      <character-ref idTarget="CompañeroClase3" x="1186" y="588" scale="0.5761287" orientation="0" layer="3" hasInfluenceArea="no">
        <condition>
          <inactive flag="EntraProfesor" />
          <active flag="Dia2" />
        </condition>
      </character-ref>
      <character-ref idTarget="Profesor" x="755" y="589" scale="0.3962661" orientation="2" layer="4" hasInfluenceArea="no">
        <condition>
          <active flag="EntraProfesor" />
        </condition>
      </character-ref>
    </characters>
    <active-areas>
      <active-area id="mesaprota" rectangular="yes" x="1513" y="612" width="347" height="238" hasInfluenceArea="no" behaviour="normal">
        <description>
          <name>
          </name>
          <brief>
          </brief>
          <detailed>
          </detailed>
        </description>
      </active-area>
    </active-areas>
    <atrezzo>
      <atrezzo-ref idTarget="IndicadorAnimo" x="1024" y="264" scale="1" layer="0" />
    </atrezzo>
  </scene>
  <scene id="PasilloColegio" start="no" playerLayer="-1" playerScale="1" class="accesible" type="area">
    <documentation>
    </documentation>
    <resources name="No name">
      <asset type="background" uri="assets/background/cole-pasillo.png" />
    </resources>
    <name>
    </name>
    <default-initial-position x="400" y="450" />
    <exits>
      <exit rectangular="yes" x="743" y="3" width="477" height="403" hasInfluenceArea="no" idTarget="Clase" destinyY="-2147483648" destinyX="-2147483648" destinyScale="1" transitionType="0" transitionTime="0" not-effects="no">
        <exit-look text="" cursor-path="" sound-path="" />
        <condition>
          <active flag="Dia2" />
        </condition>
        <post-effect>
          <trigger-conversation idTarget="cuarta_conversacion_CotilleosCompañeros" />
          <condition />
        </post-effect>
      </exit>
      <exit rectangular="yes" x="-1" y="133" width="336" height="609" hasInfluenceArea="no" idTarget="PatioCole" destinyY="-2147483648" destinyX="-2147483648" destinyScale="1" transitionType="0" transitionTime="0" not-effects="no">
        <exit-look text="" cursor-path="" sound-path="" />
      </exit>
      <exit rectangular="yes" x="1706" y="145" width="347" height="599" hasInfluenceArea="no" idTarget="SalonCasa" destinyY="-2147483648" destinyX="-2147483648" destinyScale="1" transitionType="0" transitionTime="0" not-effects="yes">
        <exit-look text="" cursor-path="" sound-path="" />
        <condition>
          <inactive flag="HablarDaniBurguer" />
          <inactive flag="HacerDesaparecerADaniYEnviarloAlPatio" />
        </condition>
        <not-effect>
          <speak-player>Si voy a casa llegaré tarde al burguer, debería salir por el patio.</speak-player>
          <condition />
        </not-effect>
      </exit>
    </exits>
    <atrezzo>
      <atrezzo-ref idTarget="IndicadorAnimo" x="1024" y="264" scale="1" layer="0" />
    </atrezzo>
  </scene>
  <scene id="PatioCole" start="no" playerLayer="-1" playerScale="1" class="accesible" type="area">
    <documentation>
    </documentation>
    <resources name="No name">
      <asset type="background" uri="assets/background/cole-patio.png" />
    </resources>
    <name>
    </name>
    <default-initial-position x="400" y="450" />
    <exits>
      <exit rectangular="yes" x="1843" y="-9" width="227" height="934" hasInfluenceArea="no" idTarget="PasilloColegio" destinyY="-2147483648" destinyX="-2147483648" destinyScale="1" transitionType="0" transitionTime="0" not-effects="no">
        <exit-look text="" cursor-path="" sound-path="" />
      </exit>
      <exit rectangular="yes" x="2" y="-34" width="375" height="949" hasInfluenceArea="no" idTarget="Calle" destinyY="-2147483648" destinyX="-2147483648" destinyScale="1" transitionType="0" transitionTime="0" not-effects="yes">
        <exit-look text="" cursor-path="" sound-path="" />
        <condition>
          <active flag="HablarDaniBurguer" />
        </condition>
        <not-effect>
          <speak-player>He quedado con Dani en el patio, debería decirle que ya estoy lista.</speak-player>
          <condition />
        </not-effect>
      </exit>
    </exits>
    <characters>
      <character-ref idTarget="Dani" x="591" y="588" scale="0.3564471" orientation="2" layer="0" hasInfluenceArea="no">
        <condition>
          <active flag="HacerDesaparecerADaniYEnviarloAlPatio" />
          <inactive flag="HablarDaniBurguer" />
        </condition>
      </character-ref>
    </characters>
    <atrezzo>
      <atrezzo-ref idTarget="IndicadorAnimo" x="1013" y="264" scale="1" layer="1" />
    </atrezzo>
  </scene>
  <scene id="SalonCasa" start="no" playerLayer="-1" playerScale="1" class="accesible" type="area">
    <documentation>
    </documentation>
    <resources name="No name">
      <asset type="background" uri="assets/background/casa-salon.png" />
    </resources>
    <name>
    </name>
    <default-initial-position x="400" y="450" />
    <exits>
      <exit rectangular="yes" x="1539" y="26" width="199" height="410" hasInfluenceArea="no" idTarget="PasilloColegio" destinyY="-2147483648" destinyX="-2147483648" destinyScale="1" transitionType="0" transitionTime="0" not-effects="no">
        <exit-look text="" cursor-path="" sound-path="" />
      </exit>
      <exit rectangular="yes" x="-15" y="15" width="305" height="421" hasInfluenceArea="no" idTarget="HabitacionCasa" destinyY="-2147483648" destinyX="-2147483648" destinyScale="1" transitionType="0" transitionTime="0" not-effects="no">
        <exit-look text="" cursor-path="" sound-path="" />
      </exit>
    </exits>
    <atrezzo>
      <atrezzo-ref idTarget="IndicadorAnimo" x="1024" y="264" scale="1" layer="0" />
    </atrezzo>
  </scene>
  <scene id="HabitacionCasa" start="no" playerLayer="-1" playerScale="1" class="accesible" type="area">
    <documentation>
    </documentation>
    <resources name="">
      <asset type="background" uri="assets/background/casa-habitacion.png" />
    </resources>
    <name>
    </name>
    <default-initial-position x="400" y="450" />
    <exits>
      <exit rectangular="yes" x="59" y="35" width="240" height="557" hasInfluenceArea="no" idTarget="SalonCasa" destinyY="-2147483648" destinyX="-2147483648" destinyScale="1" transitionType="0" transitionTime="0" not-effects="yes">
        <exit-look text="" cursor-path="" sound-path="" />
        <condition>
          <active flag="Dia2" />
        </condition>
        <not-effect>
          <speak-player>Mejor me voy a ir a la cama, que estoy muy cansada</speak-player>
          <condition />
        </not-effect>
      </exit>
    </exits>
    <active-areas>
      <active-area id="ordenador" rectangular="yes" x="783" y="270" width="159" height="100" hasInfluenceArea="no" behaviour="normal">
        <description>
          <name>
          </name>
          <brief>
          </brief>
          <detailed>
          </detailed>
        </description>
      </active-area>
      <active-area id="Cama" rectangular="yes" x="1557" y="619" width="483" height="268" hasInfluenceArea="no" behaviour="normal">
        <description>
          <name>
          </name>
          <brief>
          </brief>
          <detailed>
          </detailed>
        </description>
        <actions>
          <use needsGoTo="yes" keepDistance="35" not-effects="no">
            <effect>
              <speak-player>Estoy cansada, voy a dormir.</speak-player>
              <condition />
              <activate flag="Dia2" />
              <condition />
              <trigger-cutscene idTarget="Dormir" />
              <condition />
            </effect>
          </use>
        </actions>
      </active-area>
    </active-areas>
    <atrezzo>
      <atrezzo-ref idTarget="IndicadorAnimo" x="1024" y="264" scale="1" layer="0" />
    </atrezzo>
  </scene>
  <scene id="Burguer" start="no" playerLayer="-1" playerScale="1" class="accesible" type="area">
    <documentation>
    </documentation>
    <resources name="No name">
      <asset type="background" uri="assets/background/burger.png" />
    </resources>
    <name>
    </name>
    <default-initial-position x="400" y="450" />
    <exits>
      <exit rectangular="yes" x="1891" y="1" width="159" height="929" hasInfluenceArea="no" idTarget="SalonCasa" destinyY="-2147483648" destinyX="-2147483648" destinyScale="1" transitionType="0" transitionTime="0" not-effects="yes">
        <exit-look text="" cursor-path="" sound-path="" />
        <condition>
          <active flag="CharlaBurguer" />
        </condition>
        <not-effect>
          <speak-player>No te vayas, que estás con tus amigos!!!</speak-player>
          <condition />
        </not-effect>
      </exit>
    </exits>
    <characters>
      <character-ref idTarget="Dani" x="1303" y="658" scale="0.5984449" orientation="0" layer="0" hasInfluenceArea="no">
        <condition>
          <inactive flag="CharlaBurguer" />
        </condition>
      </character-ref>
      <character-ref idTarget="Mario" x="660" y="674" scale="0.5535784" orientation="0" layer="1" hasInfluenceArea="no">
        <condition>
          <inactive flag="CharlaBurguer" />
        </condition>
      </character-ref>
      <character-ref idTarget="Julia" x="987" y="639" scale="0.7465571" orientation="0" layer="2" hasInfluenceArea="no">
        <condition>
          <inactive flag="CharlaBurguer" />
        </condition>
      </character-ref>
    </characters>
    <active-areas>
      <active-area id="mostrador" rectangular="yes" x="2" y="166" width="290" height="384" hasInfluenceArea="no" behaviour="normal">
        <description>
          <name>
          </name>
          <brief>
          </brief>
          <detailed>
          </detailed>
        </description>
      </active-area>
    </active-areas>
    <atrezzo>
      <atrezzo-ref idTarget="IndicadorAnimo" x="1024" y="264" scale="1" layer="3" />
    </atrezzo>
  </scene>
  <scene id="Calle" start="no" playerLayer="-1" playerScale="1" class="accesible" type="area">
    <documentation>
    </documentation>
    <resources name="No name">
      <asset type="background" uri="assets/background/calle-parque.png" />
    </resources>
    <name>
    </name>
    <default-initial-position x="400" y="450" />
    <exits>
      <exit rectangular="yes" x="2" y="-30" width="164" height="872" hasInfluenceArea="no" idTarget="Burguer" destinyY="-2147483648" destinyX="-2147483648" destinyScale="1" transitionType="0" transitionTime="0" not-effects="no">
        <exit-look text="" cursor-path="" sound-path="" />
        <post-effect>
          <trigger-conversation idTarget="tercera_conversacion_Burguer" />
          <condition />
        </post-effect>
      </exit>
    </exits>
    <atrezzo>
      <atrezzo-ref idTarget="IndicadorAnimo" x="1024" y="264" scale="1" layer="0" />
    </atrezzo>
  </scene>
  <graph-conversation id="primera_conversacion_Dani">
    <dialogue-node nodeindex="0" editor-x="75" editor-y="40">
      <speak-char idTarget="Dani">¡Hey, Sandra! Menos mal que ya han terminado las clases, he estado a punto de dormirme tres veces.</speak-char>
      <condition />
      <speak-player>A mí matemáticas me ha gustado.</speak-player>
      <condition />
      <speak-char idTarget="Dani"> Siempre has sido de las raritas. </speak-char>
      <condition />
      <speak-player>Si tú lo dices… </speak-player>
      <condition />
      <speak-char idTarget="Dani">Bueno, de todas formas había venido para invitarte al burger, que vamos a ir algunos de clase. Si quieres vamos juntos.</speak-char>
      <condition />
      <child nodeindex="1" />
    </dialogue-node>
    <option-node nodeindex="1" preListening="yes" editor-x="428" editor-y="40" x="428" y="40">
      <speak-player>Claro, pero déjame recoger mis cosas. </speak-player>
      <condition />
      <child nodeindex="2" />
      <speak-player>No me apetece demasiado</speak-player>
      <condition />
      <child nodeindex="3" />
    </option-node>
    <dialogue-node nodeindex="2" editor-x="648" editor-y="40">
      <speak-char idTarget="Dani">Vale, voy tirando entonces. Nos vemos en el burguer.</speak-char>
      <condition />
      <end-conversation>
        <effect>
          <activate flag="HablarDaniBurguer" />
          <condition />
        </effect>
      </end-conversation>
    </dialogue-node>
    <dialogue-node nodeindex="3" editor-x="648" editor-y="234">
      <speak-char idTarget="Dani">¡Venga hombre, anímate! Vienen Julia y Mario. Además, no te vendría mal salir un poco y dejar tus "maniquitas"</speak-char>
      <condition />
      <speak-player>No sé...</speak-player>
      <condition />
      <speak-char idTarget="Dani">Vengaaaaaa</speak-char>
      <condition />
      <speak-player>Bueno está bien. Vamos.</speak-player>
      <condition />
      <speak-char idTarget="Dani">Genial, te espero en el patio mientras recoges tus cosas.</speak-char>
      <condition />
      <end-conversation>
        <effect>
          <activate flag="HacerDesaparecerADaniYEnviarloAlPatio" />
          <condition />
        </effect>
      </end-conversation>
    </dialogue-node>
  </graph-conversation>
  <graph-conversation id="segunda_conversacion_PatioIrAlBurguer">
    <dialogue-node nodeindex="0" editor-x="50" editor-y="49">
      <speak-char idTarget="Dani">¿Lista? Vámonos.</speak-char>
      <condition />
      <end-conversation>
        <effect>
          <activate flag="HablarDaniBurguer" />
          <condition />
          <trigger-scene idTarget="Burguer" x="1024" y="677" transitionTime="1000" transitionType="4" />
          <condition />
          <trigger-conversation idTarget="tercera_conversacion_Burguer" />
          <condition />
        </effect>
      </end-conversation>
    </dialogue-node>
  </graph-conversation>
  <graph-conversation id="tercera_conversacion_Burguer">
    <dialogue-node nodeindex="0" editor-x="58" editor-y="49">
      <speak-char idTarget="Mario">¡Hola Sandra! ¿Qué tal? Hace mucho que no salías con nosotros.</speak-char>
      <condition />
      <speak-char idTarget="Julia">¡Hey! Menos mal que has venido. ¿Sabes? Vuelvo a necesitar tu ayuda con las mates.</speak-char>
      <condition />
      <speak-char idTarget="Dani">He consiguido que saliera de su cueva.</speak-char>
      <condition />
      <speak-player>Lo siento chicos, últimamente tengo mucho que estudiar.</speak-player>
      <condition />
      <speak-char idTarget="Mario">Pero si aún queda dos meses para selectividad, ¿No te estás estresando demasiado?</speak-char>
      <condition />
      <child nodeindex="1" />
    </dialogue-node>
    <option-node nodeindex="1" preListening="yes" editor-x="507" editor-y="48" x="507" y="48">
      <speak-player>¿No será que estás tú muy relajado?</speak-player>
      <condition />
      <child nodeindex="2" />
      <speak-player>Necesito conseguir una buena nota y no lo haré estudando la semana de antes.</speak-player>
      <condition />
      <child nodeindex="3" />
      <speak-player>Supongo que tienes razón, igual debería tomármelo con más calma.</speak-player>
      <condition />
      <child nodeindex="4" />
    </option-node>
    <dialogue-node nodeindex="2" editor-x="790" editor-y="49">
      <speak-char idTarget="Mario">Ese es mi lema en la vida.</speak-char>
      <condition />
      <child nodeindex="5" />
    </dialogue-node>
    <dialogue-node nodeindex="3" editor-x="790" editor-y="243">
      <speak-char idTarget="Mario">Pero tienes tiempo de sobra.</speak-char>
      <condition />
      <child nodeindex="5" />
      <effect>
        <increment var="Animo" value="1" />
        <condition>
          <less-equals-than var="Animo" value="5" />
        </condition>
      </effect>
    </dialogue-node>
    <dialogue-node nodeindex="4" editor-x="727" editor-y="465">
      <child nodeindex="5" />
      <effect>
        <decrement var="Animo" value="1" />
        <condition>
          <greater-than var="Animo" value="0" />
        </condition>
      </effect>
    </dialogue-node>
    <dialogue-node nodeindex="5" editor-x="1096" editor-y="145">
      <speak-char idTarget="Julia">A todo esto, ¿tenéis pensado que queréis estudiar? Yo había pensado Psicología.</speak-char>
      <condition />
      <speak-char idTarget="Dani">Yo quiero entrar en Ingeniería Civil.</speak-char>
      <condition />
      <speak-char idTarget="Mario">Yo estoy entre Física y ADE.</speak-char>
      <condition />
      <speak-char idTarget="Dani">Con lo vago que eres yo que tú me iba a ADE.</speak-char>
      <condition />
      <speak-player>A mi me gustaría hacer Ingeniería Informática.</speak-player>
      <condition />
      <speak-char idTarget="Mario">...</speak-char>
      <condition />
      <speak-char idTarget="Mario">¿Pero en esa carrera hay chicas? Bueno, igualmente siempre has sido algo más marimacho.</speak-char>
      <condition />
      <child nodeindex="6" />
    </dialogue-node>
    <option-node nodeindex="6" preListening="yes" editor-x="1331" editor-y="145" x="1331" y="145">
      <speak-player>No creo que mi género influya en la carrera que quiera estudiar</speak-player>
      <condition />
      <child nodeindex="7" />
      <speak-player>Es que me interesa mucho la programación.</speak-player>
      <condition />
      <child nodeindex="8" />
      <speak-player>Bueno, igual tienes razón, tampoco quiero parecer una rara</speak-player>
      <condition />
      <child nodeindex="9" />
    </option-node>
    <dialogue-node nodeindex="7" editor-x="1549" editor-y="134">
      <speak-char idTarget="Julia">Es cierto. No seas un idiota Mario, que estamos en el siglo XXI. No llames así a Sandra.</speak-char>
      <condition />
      <child nodeindex="8" />
      <effect>
        <increment var="Animo" value="1" />
        <condition>
          <less-equals-than var="Animo" value="5" />
        </condition>
      </effect>
    </dialogue-node>
    <dialogue-node nodeindex="8" editor-x="1771" editor-y="272">
      <speak-char idTarget="Mario">Bueno, haz lo que quieras. Después de todo es tu futuro, aunque yo me lo pensaría.</speak-char>
      <condition />
      <speak-char idTarget="Dani">¡Oye! Ya viene nuestra comida. Olvidaos de los estudios ahora.</speak-char>
      <condition />
      <end-conversation>
        <effect>
          <activate flag="CharlaBurguer" />
          <condition />
          <trigger-cutscene idTarget="FinBurguer" />
          <condition />
        </effect>
      </end-conversation>
    </dialogue-node>
    <dialogue-node nodeindex="9" editor-x="1553" editor-y="394">
      <child nodeindex="8" />
      <effect>
        <decrement var="Animo" value="1" />
        <condition>
          <greater-than var="Animo" value="0" />
        </condition>
      </effect>
    </dialogue-node>
  </graph-conversation>
  <graph-conversation id="cuarta_conversacion_CotilleosCompañeros">
    <dialogue-node nodeindex="0" editor-x="50" editor-y="50">
      <speak-char idTarget="CompañeroClase1">¿Os habéis enterado de eso?</speak-char>
      <condition />
      <speak-char idTarget="CompañeroClase2">Siempre ha sido rara...</speak-char>
      <condition />
      <speak-char idTarget="CompañeroClase3">Pero... ¿eso no es muy de tíos?</speak-char>
      <condition />
      <speak-char idTarget="CompañeroClase2">Y de frikis, además.</speak-char>
      <condition />
      <end-conversation>
        <effect>
          <activate flag="CotilleosCompañeros" />
          <condition />
          <trigger-conversation idTarget="quinta_coversacion_DaniEntraAClase" />
          <condition />
        </effect>
      </end-conversation>
    </dialogue-node>
  </graph-conversation>
  <graph-conversation id="quinta_coversacion_DaniEntraAClase">
    <dialogue-node nodeindex="0" editor-x="50" editor-y="50">
      <speak-char idTarget="Dani">Buenos días, Sandra.</speak-char>
      <condition />
      <speak-player>Buenas.</speak-player>
      <condition />
      <speak-player>Oye, Dani, ¿Tienes idea de lo que están hablando?</speak-player>
      <condition />
      <speak-char idTarget="Dani">Ugh... Ignóralos, no creo que sea nada importante.</speak-char>
      <condition />
      <end-conversation>
        <effect>
          <activate flag="EntraProfesor" />
          <condition />
        </effect>
      </end-conversation>
    </dialogue-node>
  </graph-conversation>
  <atrezzoobject id="IndicadorAnimo">
    <resources name="6">
      <condition>
        <greater-equals-than var="Animo" value="6" />
      </condition>
      <asset type="image" uri="assets/image/Vida 6.png" />
      <asset type="icon" uri="assets/special/EmptyIcon.png" />
    </resources>
    <resources name="5">
      <condition>
        <equals var="Animo" value="5" />
      </condition>
      <asset type="image" uri="assets/image/Vida 5.png" />
      <asset type="icon" uri="assets/special/EmptyIcon.png" />
    </resources>
    <resources name="4">
      <condition>
        <equals var="Animo" value="4" />
      </condition>
      <asset type="image" uri="assets/image/Vida 4.png" />
      <asset type="icon" uri="assets/special/EmptyIcon.png" />
    </resources>
    <resources name="3">
      <condition>
        <equals var="Animo" value="3" />
      </condition>
      <asset type="image" uri="assets/image/Vida 3.png" />
      <asset type="icon" uri="assets/special/EmptyIcon.png" />
    </resources>
    <resources name="2">
      <condition>
        <equals var="Animo" value="2" />
      </condition>
      <asset type="image" uri="assets/image/Vida 2.png" />
      <asset type="icon" uri="assets/special/EmptyIcon.png" />
    </resources>
    <resources name="1">
      <condition>
        <equals var="Animo" value="1" />
      </condition>
      <asset type="image" uri="assets/image/Vida 1.png" />
      <asset type="icon" uri="assets/special/EmptyIcon.png" />
    </resources>
    <resources name="0">
      <condition>
        <less-equals-than var="Animo" value="0" />
      </condition>
      <asset type="image" uri="assets/image/Vacia .png" />
      <asset type="icon" uri="assets/special/EmptyIcon.png" />
    </resources>
    <description>
      <name>
      </name>
      <brief>
      </brief>
      <detailed>
      </detailed>
    </description>
  </atrezzoobject>
  <slidescene id="FinBurguer" start="no" idTarget="HabitacionCasa" destinyX="-2147483648" destinyY="2147483647" transitionTime="0" transitionType="3" next="new-scene" class="accesible" type="cutscene">
    <documentation>
    </documentation>
    <resources name="No name">
      <asset type="slides" uri="assets/animation/TransiccionBurguerCasa.eaa.xml" />
    </resources>
    <name>
    </name>
  </slidescene>
  <slidescene id="Dormir" start="no" next="go-back" class="accesible" type="cutscene">
    <documentation>
    </documentation>
    <resources name="No name">
      <asset type="slides" uri="assets/animation/dormir.eaa.xml" />
    </resources>
    <name>
    </name>
  </slidescene>
</eAdventure>